sqlite_ml/__init__.py
sqlite_ml/py.typed
sqlite_ml/sql/schema.sql
sqlite_ml/sqml.py
sqlite_ml-0.1.2.dist-info/LICENSE
sqlite_ml-0.1.2.dist-info/METADATA
sqlite_ml-0.1.2.dist-info/WHEEL
sqlite_ml-0.1.2.dist-info/RECORD
