Metadata-Version: 2.1
Name: sqlite-ml
Version: 0.1.2
Summary: An SQLite extension for machine learning
License: Apache License, Version 2.0
Author: Romain Clement
Author-email: contact@romain-clement.net
Requires-Python: >=3.8.1,<4.0.0
Classifier: License :: Other/Proprietary License
Classifier: Programming Language :: Python :: 3
Classifier: Programming Language :: Python :: 3.9
Classifier: Programming Language :: Python :: 3.10
Classifier: Programming Language :: Python :: 3.11
Requires-Dist: pandas
Requires-Dist: scikit-learn
